bridge_events/__init__.py
bridge_events/event_emitter.py
bridge_events/server.py
bridge_events/core/__init__.py
bridge_events/core/exceptions.py
bridge_events/core/protocols.py
bridge_events-1.0.2.dist-info/METADATA
bridge_events-1.0.2.dist-info/WHEEL
bridge_events-1.0.2.dist-info/licenses/LICENSE.md
bridge_events-1.0.2.dist-info/RECORD
