Metadata-Version: 2.4
Name: bridge-events
Version: 1.0.2
Summary: Pythonic adapter for Bridge events
Project-URL: Homepage, https://github.com/julienbenac/bridge-events
Author-email: Julien Benac <contact@julienbenac.fr>
License-Expression: MIT
License-File: LICENSE.md
Keywords: bridge,events,webhooks
Classifier: Development Status :: 5 - Production/Stable
Classifier: Intended Audience :: Developers
Classifier: License :: OSI Approved :: MIT License
Classifier: Operating System :: OS Independent
Classifier: Programming Language :: Python
Classifier: Programming Language :: Python :: 3 :: Only
Classifier: Programming Language :: Python :: 3.13
Classifier: Programming Language :: Python :: 3.14
Classifier: Programming Language :: Python :: 3.15
Classifier: Topic :: Communications
Classifier: Topic :: Internet
Classifier: Topic :: Software Development :: Libraries
Requires-Python: >=3.13
Requires-Dist: pyee>=13.0.0
Requires-Dist: starlette>=0.48.0
